LICENSE
MANIFEST.in
README.rst
helga_loljava.py
setup.py
helga_loljava.egg-info/PKG-INFO
helga_loljava.egg-info/SOURCES.txt
helga_loljava.egg-info/dependency_links.txt
helga_loljava.egg-info/entry_points.txt
helga_loljava.egg-info/top_level.txt
helga_loljava.egg-info/zip-safe